[
  {
    "type": "openapi",
    "url": "http://parser-service:8002",
    "spec_type": "url",
    "path": "/openapi.json",
    "auth_type": "none",
    "headers": null,
    "key": "",
    "info": {
      "id": "document_search",
      "name": "데이터 기반 검색기",
      "description": "전처리된 내부 문서, 업무보고 원문, 수리 이력, 날짜별 작업 기록을 검색해 권한에 맞는 근거와 답변을 반환합니다. PDF 생성이나 구매 품의서 생성에는 사용하지 않습니다."
    },
    "config": {
      "enable": true,
      "function_name_filter_list": "search_documents_by_rank",
      "access_grants": [
        {
          "principal_type": "user",
          "principal_id": "*",
          "permission": "read"
        }
      ]
    }
  }
]
